{
  "generated": "2026-03-30T14:37:26.995834081+00:00",
  "duration_ms": 39418,
  "instant_kpis": [
    {
      "name": "mail.* HTTPS",
      "passed": true,
      "details": "HTTP 302",
      "duration_ms": 454,
      "error": null,
      "severity": "Critical"
    },
    {
      "name": "webmail HTTPS",
      "passed": true,
      "details": "HTTP 200",
      "duration_ms": 505,
      "error": null,
      "severity": "Critical"
    },
    {
      "name": "auth HTTPS",
      "passed": true,
      "details": "HTTP 200",
      "duration_ms": 448,
      "error": null,
      "severity": "Warning"
    },
    {
      "name": "MCP endpoint",
      "passed": true,
      "details": "HTTP 400",
      "duration_ms": 5795,
      "error": null,
      "severity": "Warning"
    },
    {
      "name": "mail:993 TLS",
      "passed": true,
      "details": "TLS OK",
      "duration_ms": 904,
      "error": null,
      "severity": "Critical"
    },
    {
      "name": "mail:465 TLS",
      "passed": true,
      "details": "TLS OK",
      "duration_ms": 904,
      "error": null,
      "severity": "Critical"
    },
    {
      "name": "mail:587 STARTTLS",
      "passed": true,
      "details": "TLS OK",
      "duration_ms": 1778,
      "error": null,
      "severity": "Critical"
    },
    {
      "name": "MX record",
      "passed": false,
      "details": "NONE",
      "duration_ms": 5001,
      "error": "NONE",
      "severity": "Critical"
    },
    {
      "name": "DKIM record",
      "passed": true,
      "details": "present",
      "duration_ms": 21,
      "error": null,
      "severity": "Critical"
    },
    {
      "name": "GHA health",
      "passed": true,
      "details": "all green",
      "duration_ms": 1039,
      "error": null,
      "severity": "Info"
    }
  ],
  "preflight": [
    {
      "name": "WG oci-mail",
      "passed": true,
      "details": "10.0.0.3:22 OK",
      "duration_ms": 255,
      "error": null,
      "severity": "Critical"
    },
    {
      "name": "WG oci-apps",
      "passed": true,
      "details": "10.0.0.6:22 OK",
      "duration_ms": 247,
      "error": null,
      "severity": "Critical"
    },
    {
      "name": "WG gcp-proxy",
      "passed": true,
      "details": "10.0.0.1:22 OK",
      "duration_ms": 185,
      "error": null,
      "severity": "Critical"
    },
    {
      "name": "SSH batch oci-mail",
      "passed": false,
      "details": "SSH FAILED",
      "duration_ms": 0,
      "error": "SSH FAILED",
      "severity": "Critical"
    },
    {
      "name": "SSH batch oci-apps",
      "passed": true,
      "details": "mail-mcp: Up 14 hours",
      "duration_ms": 0,
      "error": null,
      "severity": "Warning"
    },
    {
      "name": "SSH batch gcp-proxy",
      "passed": true,
      "details": "Authelia OK",
      "duration_ms": 0,
      "error": null,
      "severity": "Warning"
    }
  ],
  "containers": [
    {
      "name": "skipped",
      "passed": false,
      "details": "SSH unreachable",
      "duration_ms": 0,
      "error": "SSH to oci-mail failed",
      "severity": "Critical"
    }
  ],
  "network": [
    {
      "name": "Caddy (gcp-proxy)",
      "passed": true,
      "details": "HTTPS OK (10.0.0.1)",
      "duration_ms": 683,
      "error": null,
      "severity": "Critical"
    },
    {
      "name": "Hickory DNS",
      "passed": true,
      "details": "stalwart.app -> 10.0.0.3",
      "duration_ms": 235,
      "error": null,
      "severity": "Critical"
    },
    {
      "name": "TLS WG direct",
      "passed": false,
      "details": "SSH down",
      "duration_ms": 0,
      "error": "SSH down",
      "severity": "Critical"
    },
    {
      "name": "Caddy L4 -> IMAP",
      "passed": true,
      "details": "993 forwarding OK",
      "duration_ms": 0,
      "error": null,
      "severity": "Critical"
    },
    {
      "name": "Caddy L4 -> SMTPS",
      "passed": true,
      "details": "465 forwarding OK",
      "duration_ms": 0,
      "error": null,
      "severity": "Critical"
    },
    {
      "name": "Caddy L4 -> SMTP",
      "passed": true,
      "details": "587 forwarding OK",
      "duration_ms": 0,
      "error": null,
      "severity": "Critical"
    },
    {
      "name": "mail:993 (IMAP)",
      "passed": true,
      "details": "TLS OK",
      "duration_ms": 900,
      "error": null,
      "severity": "Critical"
    },
    {
      "name": "mail:465 (SMTPS)",
      "passed": true,
      "details": "TLS OK",
      "duration_ms": 899,
      "error": null,
      "severity": "Critical"
    },
    {
      "name": "mail:587 (SMTP Sub)",
      "passed": true,
      "details": "TLS OK",
      "duration_ms": 1799,
      "error": null,
      "severity": "Critical"
    },
    {
      "name": "SMTP :25 relay",
      "passed": false,
      "details": "no data",
      "duration_ms": 0,
      "error": "no data",
      "severity": "Warning"
    },
    {
      "name": "SMTP :587 local TLS",
      "passed": false,
      "details": "no data",
      "duration_ms": 0,
      "error": "no data",
      "severity": "Warning"
    },
    {
      "name": "Webmail HTTPS",
      "passed": true,
      "details": "HTTP 302",
      "duration_ms": 541,
      "error": null,
      "severity": "Warning"
    },
    {
      "name": "Webmail internal",
      "passed": false,
      "details": "no data",
      "duration_ms": 0,
      "error": "no data",
      "severity": "Warning"
    },
    {
      "name": "SnappyMail internal",
      "passed": false,
      "details": "no data",
      "duration_ms": 0,
      "error": "no data",
      "severity": "Warning"
    },
    {
      "name": "ManageSieve :4190",
      "passed": false,
      "details": "no data",
      "duration_ms": 0,
      "error": "no data",
      "severity": "Warning"
    },
    {
      "name": "Authelia health",
      "passed": true,
      "details": "Authelia OK",
      "duration_ms": 0,
      "error": null,
      "severity": "Warning"
    },
    {
      "name": "OIDC bearer -> webmail",
      "passed": true,
      "details": "Bearer auth -> 200 OK (full chain)",
      "duration_ms": 700,
      "error": null,
      "severity": "Warning"
    },
    {
      "name": "Stalwart Admin via Bearer",
      "passed": true,
      "details": "HTTP 401",
      "duration_ms": 700,
      "error": null,
      "severity": "Warning"
    },
    {
      "name": "mcp->DNS resolve",
      "passed": true,
      "details": "-> 35.226.147.64",
      "duration_ms": 0,
      "error": null,
      "severity": "Warning"
    },
    {
      "name": "mcp->IMAP TLS",
      "passed": true,
      "details": "OK proto=TLSv1.3 cn=mail.diegonmarcos.com",
      "duration_ms": 0,
      "error": null,
      "severity": "Warning"
    },
    {
      "name": "mcp->SMTP TLS",
      "passed": true,
      "details": "OK proto=TLSv1.3",
      "duration_ms": 0,
      "error": null,
      "severity": "Warning"
    },
    {
      "name": "mcp->IMAP WG direct",
      "passed": true,
      "details": "10.0.0.3:993 OK proto=TLSv1.3",
      "duration_ms": 0,
      "error": null,
      "severity": "Warning"
    },
    {
      "name": "mcp->IMAP LOGIN",
      "passed": true,
      "details": "LOGIN_OK\nTIMEOUT",
      "duration_ms": 0,
      "error": null,
      "severity": "Warning"
    },
    {
      "name": "mcp->SMTP AUTH",
      "passed": true,
      "details": "SMTP_AUTH_OK: 250-AUTH PLAIN LOGIN\r\nSMTP_AUTH_OK: 250-AUTH PLAIN LOGIN\r\nERR:write after end\nTIMEOUT",
      "duration_ms": 0,
      "error": null,
      "severity": "Warning"
    },
    {
      "name": "mail-mcp MCP",
      "passed": true,
      "details": "HTTP 400 (alive)",
      "duration_ms": 744,
      "error": null,
      "severity": "Warning"
    },
    {
      "name": "All ports bound",
      "passed": false,
      "details": "no data",
      "duration_ms": 0,
      "error": "no data",
      "severity": "Critical"
    }
  ],
  "dns_auth": [
    {
      "name": "MX",
      "passed": true,
      "details": "22 route1.mx.cloudflare.net.",
      "duration_ms": 31,
      "error": null,
      "severity": "Critical"
    },
    {
      "name": "DKIM",
      "passed": true,
      "details": "present",
      "duration_ms": 30,
      "error": null,
      "severity": "Critical"
    },
    {
      "name": "SPF",
      "passed": true,
      "details": "v=spf1",
      "duration_ms": 32,
      "error": null,
      "severity": "Critical"
    },
    {
      "name": "DMARC",
      "passed": true,
      "details": "v=DMARC1; p=reject; sp=reject; rua=mailto:postmaster@diegonmarcos.com; ruf=mailto:postmaster@diegonmarcos.com; fo=1",
      "duration_ms": 29,
      "error": null,
      "severity": "Critical"
    }
  ],
  "internals": [
    {
      "name": "skipped",
      "passed": false,
      "details": "SSH unreachable",
      "duration_ms": 0,
      "error": "SSH to oci-mail failed",
      "severity": "Critical"
    }
  ],
  "e2e_delivery": [
    {
      "name": "Resend API key",
      "passed": true,
      "details": "found",
      "duration_ms": 0,
      "error": null,
      "severity": "Info"
    },
    {
      "name": "Send via Resend",
      "passed": true,
      "details": "id=299be2bb-d46f-4b9c-adea-43e97948118c",
      "duration_ms": 381,
      "error": null,
      "severity": "Info"
    },
    {
      "name": "Resend status",
      "passed": true,
      "details": "sent (IMAP is truth)",
      "duration_ms": 4403,
      "error": null,
      "severity": "Info"
    },
    {
      "name": "IMAP arrival",
      "passed": false,
      "details": "SSH down",
      "duration_ms": 0,
      "error": "SSH down",
      "severity": "Critical"
    },
    {
      "name": "smtp-proxy logs",
      "passed": false,
      "details": "SSH down",
      "duration_ms": 0,
      "error": "SSH down",
      "severity": "Warning"
    },
    {
      "name": "CF Worker",
      "passed": true,
      "details": "info: no CF creds",
      "duration_ms": 0,
      "error": null,
      "severity": "Info"
    }
  ],
  "summary": {
    "total_checks": 54,
    "passed": 41,
    "failed": 13,
    "warnings": 6,
    "critical": 7
  },
  "timers": {
    "P6_e2e_delivery": 4784,
    "P2_containers": 0,
    "P0_instant_kpis": 7574,
    "P3_network": 1800,
    "TOTAL": 39418,
    "P2-P5_parallel": 1800,
    "P4_dns_auth": 1800,
    "P1_preflight": 25258,
    "P5_internals": 0
  }
}